pyqcloud_sdk/__init__.py
pyqcloud_sdk/base.py
pyqcloud_sdk/config.py
pyqcloud_sdk/exceptions.py
pyqcloud_sdk/logging.py
pyqcloud_sdk/services.py
pyqcloud_sdk/data/.sdk-version
pyqcloud_sdk/data/endpoints.json
pyqcloud_sdk-0.0.4.dist-info/METADATA
pyqcloud_sdk-0.0.4.dist-info/WHEEL
pyqcloud_sdk-0.0.4.dist-info/licenses/LICENSE
pyqcloud_sdk-0.0.4.dist-info/RECORD
