Metadata-Version: 2.4
Name: pyqcloud-sdk
Version: 0.0.4
Summary: A wrapper for tencentcloud-sdk-python-common
Project-URL: Homepage, https://github.com/YongSangUn/pyqcloud-sdk
Project-URL: Source, https://github.com/YongSangUn/pyqcloud-sdk
Project-URL: Tracker, https://github.com/YongSangUn/pyqcloud-sdk/issues
Author-email: YongSangUn <sangun.yong@gmail.com>
License: MIT
License-File: LICENSE
Keywords: python,sdk,tencentcloud,wrapper
Classifier: Development Status :: 3 - Alpha
Classifier: Intended Audience :: Developers
Classifier: License :: OSI Approved :: MIT License
Classifier: Programming Language :: Python :: 3
Classifier: Programming Language :: Python :: 3.6
Classifier: Programming Language :: Python :: 3.7
Classifier: Programming Language :: Python :: 3.8
Classifier: Programming Language :: Python :: 3.9
Classifier: Programming Language :: Python :: 3.10
Classifier: Programming Language :: Python :: 3.11
Classifier: Programming Language :: Python :: 3.12
Requires-Python: >=3.6
Requires-Dist: requests
Requires-Dist: tencentcloud-sdk-python-common>=3.0.1182
